Metadata-Version: 2.1
Name: termwriter
Version: 1.0.0
Summary: Organize your terminal output.
Home-page: https://github.com/markuskimius/termwriter-py
Author: Mark Kim
Author-email: markuskimius+py@gmail.com
License: Apache 2.0
Keywords: screen,stdout
Platform: UNKNOWN
